datatypesoptimizer/__init__.py
datatypesoptimizer/dataOptimizer.py
datatypesoptimizer-0.1.2.dist-info/METADATA
datatypesoptimizer-0.1.2.dist-info/WHEEL
datatypesoptimizer-0.1.2.dist-info/entry_points.txt
datatypesoptimizer-0.1.2.dist-info/RECORD
