Metadata-Version: 2.4
Name: datatypesoptimizer
Version: 0.1.2
Summary: A robost data type optimizer for pandas dataframe
Author-email: RAGHAVVRAM JOHNSON <raghavvram.johnson@gmail.com>
License-Expression: MIT
Classifier: License :: OSI Approved :: MIT License
Classifier: Operating System :: OS Independent
Classifier: Programming Language :: Python :: 3
Requires-Python: >=3.12
Requires-Dist: pandas>=2.3.1
